hsml/__init__.py
hsml/connection.py
hsml/constants.py
hsml/decorators.py
hsml/deployable_component.py
hsml/deployable_component_logs.py
hsml/deployment.py
hsml/inference_batcher.py
hsml/inference_endpoint.py
hsml/inference_logger.py
hsml/kafka_topic.py
hsml/model.py
hsml/model_registry.py
hsml/model_schema.py
hsml/model_serving.py
hsml/predictor.py
hsml/predictor_state.py
hsml/predictor_state_condition.py
hsml/resources.py
hsml/schema.py
hsml/tag.py
hsml/transformer.py
hsml/util.py
hsml/version.py
hsml/client/__init__.py
hsml/client/auth.py
hsml/client/base.py
hsml/client/exceptions.py
hsml/client/hopsworks/__init__.py
hsml/client/hopsworks/base.py
hsml/client/hopsworks/external.py
hsml/client/hopsworks/internal.py
hsml/client/istio/__init__.py
hsml/client/istio/base.py
hsml/client/istio/external.py
hsml/client/istio/internal.py
hsml/client/istio/grpc/__init__.py
hsml/client/istio/grpc/errors.py
hsml/client/istio/grpc/exceptions.py
hsml/client/istio/grpc/inference_client.py
hsml/client/istio/grpc/proto/__init__.py
hsml/client/istio/grpc/proto/grpc_predict_v2_pb2.py
hsml/client/istio/grpc/proto/grpc_predict_v2_pb2.pyi
hsml/client/istio/grpc/proto/grpc_predict_v2_pb2_grpc.py
hsml/client/istio/utils/__init__.py
hsml/client/istio/utils/infer_type.py
hsml/client/istio/utils/numpy_codec.py
hsml/core/__init__.py
hsml/core/dataset_api.py
hsml/core/explicit_provenance.py
hsml/core/model_api.py
hsml/core/model_registry_api.py
hsml/core/model_serving_api.py
hsml/core/native_hdfs_api.py
hsml/core/serving_api.py
hsml/engine/__init__.py
hsml/engine/hopsworks_engine.py
hsml/engine/local_engine.py
hsml/engine/model_engine.py
hsml/engine/serving_engine.py
hsml/python/__init__.py
hsml/python/model.py
hsml/python/predictor.py
hsml/python/signature.py
hsml/sklearn/__init__.py
hsml/sklearn/model.py
hsml/sklearn/predictor.py
hsml/sklearn/signature.py
hsml/tensorflow/__init__.py
hsml/tensorflow/model.py
hsml/tensorflow/predictor.py
hsml/tensorflow/signature.py
hsml/torch/__init__.py
hsml-3.9.0.dev1.dist-info/LICENSE
hsml-3.9.0.dev1.dist-info/METADATA
hsml-3.9.0.dev1.dist-info/WHEEL
hsml-3.9.0.dev1.dist-info/top_level.txt
hsml-3.9.0.dev1.dist-info/RECORD
