Metadata-Version: 2.1
Name: hsml
Version: 3.9.0.dev1
Summary: HSML Python SDK to interact with Hopsworks Model Registry
Author-email: Hopsworks AB <robin@hopswors.ai>
License: Apache-2.0
Project-URL: Documentation, https://docs.hopsworks.ai/latest
Project-URL: Repository, https://github.com/logicalclocks/machine-learning-api
Project-URL: Homepage, https://www.hopsworks.ai
Project-URL: Community, https://community.hopsworks.ai
Keywords: Hopsworks,Model Registry,hsml,Models,ML,Machine Learning Models,TensorFlow,PyTorch,Machine Learning,MLOps,DataOps
Classifier: Development Status :: 5 - Production/Stable
Classifier: Topic :: Utilities
Classifier: License :: OSI Approved :: Apache Software License
Classifier: Programming Language :: Python :: 3
Classifier: Programming Language :: Python :: 3.8
Classifier: Programming Language :: Python :: 3.9
Classifier: Programming Language :: Python :: 3.10
Classifier: Programming Language :: Python :: 3.11
Classifier: Programming Language :: Python :: 3.12
Classifier: Intended Audience :: Developers
Requires-Python: <3.13,>=3.8
License-File: LICENSE
Requires-Dist: pyhumps ==1.6.1
Requires-Dist: requests
Requires-Dist: furl
Requires-Dist: boto3
Requires-Dist: pandas
Requires-Dist: numpy
Requires-Dist: pyjks
Requires-Dist: mock
Requires-Dist: tqdm
Requires-Dist: grpcio <2.0.0,>=1.49.1
Requires-Dist: protobuf <4.0.0,>=3.19.0
Provides-Extra: dev
Requires-Dist: pytest ==7.4.4 ; extra == 'dev'
Requires-Dist: pytest-mock ==3.12.0 ; extra == 'dev'
Requires-Dist: ruff ; extra == 'dev'
